Metadata-Version: 2.1
Name: D2LValence-UtilTUT
Version: 0.1.16
Summary: D2LValence utility library for Python.
Home-page: http://www.desire2learn.com/r/valencehome
Author: Desire2Learn Inc.
Author-email: Valence@Desire2Learn.com
License: -*- coding: utf-8 -*-
Platform: UNKNOWN
Classifier: Development Status :: 3 - Alpha
Classifier: Intended Audience :: Developers
Classifier: Natural Language :: English
Classifier: License :: OSI Approved :: Apache Software License
Classifier: Programming Language :: Python
Classifier: Programming Language :: Python :: 3
Classifier: Programming Language :: Python :: 3.0
Classifier: Programming Language :: Python :: 3.1
Classifier: Programming Language :: Python :: 3.2
Classifier: Programming Language :: Python :: 3.3
License-File: LICENSE
